LICENCE.txt
MANIFEST.in
README.rst
pyproject.toml
setup.cfg
setup.py
django_deovi/__init__.py
django_deovi/apps.py
django_deovi/dump.py
django_deovi/exceptions.py
django_deovi/loader.py
django_deovi/outputs.py
django_deovi/routers.py
django_deovi/search_fields.py
django_deovi/search_indexes.py
django_deovi/settings.py
django_deovi/urls.py
django_deovi.egg-info/PKG-INFO
django_deovi.egg-info/SOURCES.txt
django_deovi.egg-info/dependency_links.txt
django_deovi.egg-info/requires.txt
django_deovi.egg-info/top_level.txt
django_deovi.egg-info/zip-safe
django_deovi/admin/__init__.py
django_deovi/admin/device.py
django_deovi/admin/directory.py
django_deovi/admin/media.py
django_deovi/factories/__init__.py
django_deovi/factories/device.py
django_deovi/factories/directory.py
django_deovi/factories/dump.py
django_deovi/factories/media.py
django_deovi/factories/user.py
django_deovi/form_helpers/__init__.py
django_deovi/form_helpers/default.py
django_deovi/form_helpers/layout_objects.py
django_deovi/form_helpers/search.py
django_deovi/forms/__init__.py
django_deovi/forms/search.py
django_deovi/management/commands/__init__.py
django_deovi/management/commands/load_medias.py
django_deovi/migrations/0001_initial.py
django_deovi/migrations/0002_alter_directory_options_alter_mediafile_options_and_more.py
django_deovi/migrations/0003_device_last_update.py
django_deovi/migrations/0004_add_device_disk_usage_fields.py
django_deovi/migrations/__init__.py
django_deovi/models/__init__.py
django_deovi/models/device.py
django_deovi/models/directory.py
django_deovi/models/media.py
django_deovi/serializers/__init__.py
django_deovi/serializers/media.py
django_deovi/templates/bootstrap5/layout/listgroupcheckboxes.html
django_deovi/templates/django_deovi/base.html
django_deovi/templates/django_deovi/mediafile_detail.html
django_deovi/templates/django_deovi/pagination.html
django_deovi/templates/django_deovi/device/_occupancy.svg
django_deovi/templates/django_deovi/device/_tree-item.html
django_deovi/templates/django_deovi/device/detail.html
django_deovi/templates/django_deovi/device/index.html
django_deovi/templates/django_deovi/device/tree.html
django_deovi/templates/django_deovi/directory/detail.html
